bods_client/__init__.py
bods_client/client.py
bods_client/constants.py
bods_client/models/__init__.py
bods_client/models/avl.py
bods_client/models/base.py
bods_client/models/fares.py
bods_client/models/siri.py
bods_client/models/timetables.py
bods_client/py.typed
bods_client/types.py
bods_client-0.13.0.dist-info/LICENSE
bods_client-0.13.0.dist-info/METADATA
bods_client-0.13.0.dist-info/WHEEL
bods_client-0.13.0.dist-info/RECORD
