Metadata-Version: 2.1
Name: bods-client
Version: 0.13.0
Summary: A Python client for the Department for Transport Bus Open Data Service API
Home-page: https://github.com/ciaranmccormick/python-bods-client
License: MIT
Keywords: BODS,bus,open data,TXC,transxchange
Author: Ciaran McCormick
Requires-Python: >=3.9,<4.0
Classifier: Development Status :: 3 - Alpha
Classifier: Intended Audience :: Developers
Classifier: License :: OSI Approved :: MIT License
Classifier: Operating System :: OS Independent
Classifier: Programming Language :: Python :: 3
Classifier: Programming Language :: Python :: 3.9
Classifier: Programming Language :: Python :: 3.10
Classifier: Programming Language :: Python :: 3.11
Classifier: Programming Language :: Python :: 3.12
Classifier: Topic :: Software Development :: Libraries :: Python Modules
Requires-Dist: gtfs-realtime-bindings (>=1.0.0,<2.0.0)
Requires-Dist: importlib-metadata (>=4.0.0,<5.0.0)
Requires-Dist: lxml (>=4.7.1,<5.0.0)
Requires-Dist: protobuf (>=3.20.0,<4.0.0)
Requires-Dist: pydantic (>=2.8,<2.9)
Requires-Dist: python-dateutil (>=2.8,<2.9)
Requires-Dist: requests (>=2.25.0,<3.0.0)
Project-URL: Repository, https://github.com/ciaranmccormick/python-bods-client
